pipenode/__init__.py
pipenode/clients.py
pipenode/error.py
pipenode/log.py
pipenode/model.py
pipenode/server.py
pipenode/task_protocal.py
pipenode/tasks.py
pipenode/endpoints/__init__.py
pipenode/endpoints/http_endpoints.py
pipenode/endpoints/nsq_endpoints.py
pipenode/endpoints/rabbitmq_endpoints.py
pipenode/endpoints/redis_endpoints.py
pipenode/endpoints/time_endpoints.py
pipenode-0.381.dist-info/METADATA
pipenode-0.381.dist-info/WHEEL
pipenode-0.381.dist-info/top_level.txt
pipenode-0.381.dist-info/RECORD
