Metadata-Version: 2.1
Name: pipenode
Version: 0.381
Summary: A clone of Spotify's Luigi library with less features and intended for workflows on a single machine.
Home-page: https://gitee.com/Harlaus/pipenode
Author: qize.luo
Author-email: qize.luo@miniso.com
License: UNKNOWN
Download-URL: https://gitee.com/Harlaus/pipenode/archive/0.5.tar.gz
Keywords: python,workflow
Platform: UNKNOWN
Classifier: Programming Language :: Python :: 3
Classifier: License :: OSI Approved :: MIT License
Classifier: Operating System :: OS Independent
